utaw/__init__.py
utaw/assertions.py
utaw-0.2.0.dist-info/DESCRIPTION.rst
utaw-0.2.0.dist-info/METADATA
utaw-0.2.0.dist-info/RECORD
utaw-0.2.0.dist-info/WHEEL
utaw-0.2.0.dist-info/metadata.json
utaw-0.2.0.dist-info/top_level.txt
