Metadata-Version: 2.0
Name: utaw
Version: 0.2.0
Summary: UTAW: UnitTest Assertion Wrapper.
Home-page: https://github.com/notion/utaw
Author: toejough
Author-email: toejough@gmail.com
License: UNKNOWN
Keywords: test assert assertions
Platform: UNKNOWN
Classifier: Development Status :: 4 - Beta
Classifier: Intended Audience :: Developers
Classifier: License :: OSI Approved :: Apache Software License
Classifier: Programming Language :: Python :: 3
Classifier: Programming Language :: Python :: 3.5
Classifier: Programming Language :: Python :: 3.6
